ProMaid/Errors.py
ProMaid/__init__.py
ProMaid/keyword_enum.py
ProMaid/pml_parser.py
ProMaid/prompt_tree_node.py
promaid-0.1.0.dist-info/METADATA
promaid-0.1.0.dist-info/WHEEL
promaid-0.1.0.dist-info/top_level.txt
promaid-0.1.0.dist-info/RECORD
