Metadata-Version: 2.1
Name: promaid
Version: 0.1.0
Summary: A markup language that can fill data into prompt
Author: Eterance
Keywords: Prompt,Markup Language,NLP,AI,GPT
Classifier: Programming Language :: Python :: 3
Classifier: License :: OSI Approved :: MIT License
Classifier: Operating System :: OS Independent
Requires-Python: >=3.6
